wsgi_mod_rpaf.py
wsgi_mod_rpaf-3.0.0.dist-info/DESCRIPTION.rst
wsgi_mod_rpaf-3.0.0.dist-info/METADATA
wsgi_mod_rpaf-3.0.0.dist-info/RECORD
wsgi_mod_rpaf-3.0.0.dist-info/WHEEL
wsgi_mod_rpaf-3.0.0.dist-info/metadata.json
wsgi_mod_rpaf-3.0.0.dist-info/top_level.txt
