Metadata-Version: 2.0
Name: wsgi-mod-rpaf
Version: 3.0.0
Summary: WSGI middleware implementing apache mod-rpaf
Home-page: https://github.com/Yelp/wsgi-mod-rpaf
Author: Anthony Sottile
Author-email: asottile@umich.edu
License: UNKNOWN
Platform: UNKNOWN
Classifier: License :: OSI Approved :: MIT License
Classifier: Programming Language :: Python :: 2
Classifier: Programming Language :: Python :: 2.7
Classifier: Programming Language :: Python :: 3
Classifier: Programming Language :: Python :: 3.5
Classifier: Programming Language :: Python :: Implementation :: CPython
Classifier: Programming Language :: Python :: Implementation :: PyPy
Requires-Dist: six
Requires-Dist: ipaddress; python_version=="2.7"
